InstructionCLI/__init__.py
InstructionCLI/applyParameter.py
InstructionCLI/applyParameters.py
InstructionCLI/cli.py
InstructionCLI/config.py
InstructionCLI/exception.py
InstructionCLI/instruction.py
instructioncli-0.0.4.dist-info/METADATA
instructioncli-0.0.4.dist-info/WHEEL
instructioncli-0.0.4.dist-info/licenses/LICENSE
instructioncli-0.0.4.dist-info/RECORD
